msnhnet_onnx/__init__.py
msnhnet_onnx/constants.py
msnhnet_onnx/onnx_wrapper.py
msnhnet_onnx/schemas.py
msnhnet_onnx/util.py
msnhnet_onnx/x2msnhnet/__init__.py
msnhnet_onnx/x2msnhnet/handler.py
msnhnet_onnx/x2msnhnet/onnx2msnhnet.py
msnhnet_onnx/x2msnhnet/util.py
msnhnet_onnx/x2msnhnet/handlers/__init__.py
msnhnet_onnx/x2msnhnet/handlers/array.py
msnhnet_onnx/x2msnhnet/handlers/global_var.py
msnhnet_onnx/x2msnhnet/handlers/nn.py
msnhnet_onnx-0.0.1.dist-info/LICENSE
msnhnet_onnx-0.0.1.dist-info/METADATA
msnhnet_onnx-0.0.1.dist-info/WHEEL
msnhnet_onnx-0.0.1.dist-info/top_level.txt
msnhnet_onnx-0.0.1.dist-info/RECORD
