Metadata-Version: 2.1
Name: msnhnet-onnx
Version: 0.0.1
Summary: a toolkit for converting ONNX model to msnhnet.
Home-page: https://github.com/BBuf/msnhnet-onnx
Author: zhangxiaoyu
Author-email: 1182563586@qq.com
License: Apache 2.0
Platform: UNKNOWN
Classifier: Programming Language :: Python :: 3
Classifier: License :: OSI Approved :: Apache Software License
Classifier: Operating System :: OS Independent
Requires-Dist: six
Requires-Dist: protobuf
